{
  "data": {
    "pagination": {
      "cur_page": 1,
      "page_size": 10,
      "total_page": 1,
      "record_count": 5,
      "pre": 1,
      "next": 1,
      "start": 0,
      "end": 10
    },
    "items": [{
      "prize_id": "334832094208121942",
      "activity_id": "334460880296576542",
      "coupon_id": "326084653094005537",
      "amount": 0,
      "amount_format": 0.00,
      "prize_order": 2,
      "prize_name": "168元",
      "quantity": 1,
      "coupon_value": 16800,
      "coupon_value_format": "1,000.00",
      "prize_type": 2,
      "prize_type_format": "优惠券",
      "coupon_type": 1,
      "coupon_type_format": "满减",
      "image_file_id": "334832090572266689",
      "image_url": "https://sili-pr.oss-cn-shenzhen.aliyuncs.com/null"
    }, {
      "prize_id": "334832094208121942",
      "activity_id": "334460880296576542",
      "coupon_id": "326084653094005537",
      "amount": 0,
      "amount_format": 0.00,
      "prize_order": 2,
      "prize_name": "168元",
      "quantity": 1,
      "coupon_value": 16800,
      "coupon_value_format": "168.00",
      "prize_type": 2,
      "prize_type_format": "优惠券",
      "coupon_type": 1,
      "coupon_type_format": "满减",
      "image_file_id": "334832090572266689",
      "image_url": "https://sili-pr.oss-cn-shenzhen.aliyuncs.com/null"
    }, {
      "prize_id": "334832094208121942",
      "activity_id": "334460880296576542",
      "coupon_id": "326084653094005537",
      "amount": 0,
      "amount_format": 0.00,
      "prize_order": 2,
      "prize_name": "168元",
      "quantity": 1,
      "coupon_value": 16800,
      "coupon_value_format": "168.00",
      "prize_type": 2,
      "prize_type_format": "优惠券",
      "coupon_type": 1,
      "coupon_type_format": "满减",
      "image_file_id": "334832090572266689",
      "image_url": "https://sili-pr.oss-cn-shenzhen.aliyuncs.com/null"
    }, {
      "prize_id": "334832094208121942",
      "activity_id": "334460880296576542",
      "coupon_id": "326084653094005537",
      "amount": 0,
      "amount_format": 0.00,
      "prize_order": 2,
      "prize_name": "168元",
      "quantity": 1,
      "coupon_value": 16800,
      "coupon_value_format": "168.00",
      "prize_type": 2,
      "prize_type_format": "优惠券",
      "coupon_type": 1,
      "coupon_type_format": "满减",
      "image_file_id": "334832090572266689",
      "image_url": "https://sili-pr.oss-cn-shenzhen.aliyuncs.com/null"
    }, {
      "prize_id": "334832094208121942",
      "activity_id": "334460880296576542",
      "coupon_id": "326084653094005537",
      "amount": 0,
      "amount_format": 0.00,
      "prize_order": 2,
      "prize_name": "168元",
      "quantity": 1,
      "coupon_value": 16800,
      "coupon_value_format": "168.00",
      "prize_type": 2,
      "prize_type_format": "优惠券",
      "coupon_type": 1,
      "coupon_type_format": "满减",
      "image_file_id": "334832090572266689",
      "image_url": "https://sili-pr.oss-cn-shenzhen.aliyuncs.com/null"
    }, {
      "prize_id": "334832094208121942",
      "activity_id": "334460880296576542",
      "coupon_id": "326084653094005537",
      "amount": 0,
      "amount_format": 0.00,
      "prize_order": 2,
      "prize_name": "168元",
      "quantity": 1,
      "coupon_value": 16800,
      "coupon_value_format": "168.00",
      "prize_type": 2,
      "prize_type_format": "优惠券",
      "coupon_type": 1,
      "coupon_type_format": "满减",
      "image_file_id": "334832090572266689",
      "image_url": "https://sili-pr.oss-cn-shenzhen.aliyuncs.com/null"
    }, {
      "prize_id": "334832094208121942",
      "activity_id": "334460880296576542",
      "coupon_id": "326084653094005537",
      "amount": 0,
      "amount_format": 0.00,
      "prize_order": 2,
      "prize_name": "168元",
      "quantity": 1,
      "coupon_value": 16800,
      "coupon_value_format": "168.00",
      "prize_type": 2,
      "prize_type_format": "优惠券",
      "coupon_type": 1,
      "coupon_type_format": "满减",
      "image_file_id": "334832090572266689",
      "image_url": "https://sili-pr.oss-cn-shenzhen.aliyuncs.com/null"
    }, {
      "prize_id": "334832094208121942",
      "activity_id": "334460880296576542",
      "coupon_id": "326084653094005537",
      "amount": 0,
      "amount_format": 0.00,
      "prize_order": 2,
      "prize_name": "168元",
      "quantity": 1,
      "coupon_value": 16800,
      "coupon_value_format": "168.00",
      "prize_type": 2,
      "prize_type_format": "优惠券",
      "coupon_type": 1,
      "coupon_type_format": "满减",
      "image_file_id": "334832090572266689",
      "image_url": "https://sili-pr.oss-cn-shenzhen.aliyuncs.com/null"
    }, {
      "prize_id": "334832094208121942",
      "activity_id": "334460880296576542",
      "coupon_id": "326084653094005537",
      "amount": 0,
      "amount_format": 0.00,
      "prize_order": 2,
      "prize_name": "168元",
      "quantity": 1,
      "coupon_value": 16800,
      "coupon_value_format": "168.00",
      "prize_type": 2,
      "prize_type_format": "优惠券",
      "coupon_type": 1,
      "coupon_type_format": "满减",
      "image_file_id": "334832090572266689",
      "image_url": "https://sili-pr.oss-cn-shenzhen.aliyuncs.com/null"
    }, {
      "prize_id": "334832094208121942",
      "activity_id": "334460880296576542",
      "coupon_id": "326084653094005537",
      "amount": 0,
      "amount_format": 0.00,
      "prize_order": 2,
      "prize_name": "168元",
      "quantity": 1,
      "coupon_value": 16800,
      "coupon_value_format": "168.00",
      "prize_type": 2,
      "prize_type_format": "优惠券",
      "coupon_type": 1,
      "coupon_type_format": "满减",
      "image_file_id": "334832090572266689",
      "image_url": "https://sili-pr.oss-cn-shenzhen.aliyuncs.com/null"
    }, {
      "prize_id": "334832094208121942",
      "activity_id": "334460880296576542",
      "coupon_id": "326084653094005537",
      "amount": 0,
      "amount_format": 0.00,
      "prize_order": 2,
      "prize_name": "168元",
      "quantity": 1,
      "coupon_value": 16800,
      "coupon_value_format": "168.00",
      "prize_type": 2,
      "prize_type_format": "优惠券",
      "coupon_type": 1,
      "coupon_type_format": "满减",
      "image_file_id": "334832090572266689",
      "image_url": "https://sili-pr.oss-cn-shenzhen.aliyuncs.com/null"
    }, {
      "prize_id": "334832094208121942",
      "activity_id": "334460880296576542",
      "coupon_id": "326084653094005537",
      "amount": 0,
      "amount_format": 0.00,
      "prize_order": 2,
      "prize_name": "168元",
      "quantity": 1,
      "coupon_value": 16800,
      "coupon_value_format": "168.00",
      "prize_type": 2,
      "prize_type_format": "优惠券",
      "coupon_type": 1,
      "coupon_type_format": "满减",
      "image_file_id": "334832090572266689",
      "image_url": "https://sili-pr.oss-cn-shenzhen.aliyuncs.com/null"
    }, {
      "prize_id": "334832094208121942",
      "activity_id": "334460880296576542",
      "coupon_id": "326084653094005537",
      "amount": 0,
      "amount_format": 0.00,
      "prize_order": 2,
      "prize_name": "168元",
      "quantity": 1,
      "coupon_value": 16800,
      "coupon_value_format": "168.00",
      "prize_type": 2,
      "prize_type_format": "优惠券",
      "coupon_type": 1,
      "coupon_type_format": "满减",
      "image_file_id": "334832090572266689",
      "image_url": "https://sili-pr.oss-cn-shenzhen.aliyuncs.com/null"
    }, {
      "prize_id": "334832094208121942",
      "activity_id": "334460880296576542",
      "coupon_id": "326084653094005537",
      "amount": 0,
      "amount_format": 0.00,
      "prize_order": 2,
      "prize_name": "168元",
      "quantity": 1,
      "coupon_value": 16800,
      "coupon_value_format": "168.00",
      "prize_type": 2,
      "prize_type_format": "优惠券",
      "coupon_type": 1,
      "coupon_type_format": "满减",
      "image_file_id": "334832090572266689",
      "image_url": "https://sili-pr.oss-cn-shenzhen.aliyuncs.com/null"
    }, {
      "prize_id": "334832094208121942",
      "activity_id": "334460880296576542",
      "coupon_id": "326084653094005537",
      "amount": 0,
      "amount_format": 0.00,
      "prize_order": 2,
      "prize_name": "168元",
      "quantity": 1,
      "coupon_value": 16800,
      "coupon_value_format": "168.00",
      "prize_type": 2,
      "prize_type_format": "优惠券",
      "coupon_type": 1,
      "coupon_type_format": "满减",
      "image_file_id": "334832090572266689",
      "image_url": "https://sili-pr.oss-cn-shenzhen.aliyuncs.com/null"
    }, {
      "prize_id": "334832094208121942",
      "activity_id": "334460880296576542",
      "coupon_id": "326084653094005537",
      "amount": 0,
      "amount_format": 0.00,
      "prize_order": 2,
      "prize_name": "168元",
      "quantity": 1,
      "coupon_value": 16800,
      "coupon_value_format": "168.00",
      "prize_type": 2,
      "prize_type_format": "优惠券",
      "coupon_type": 1,
      "coupon_type_format": "满减",
      "image_file_id": "334832090572266689",
      "image_url": "https://sili-pr.oss-cn-shenzhen.aliyuncs.com/null"
    }, {
      "prize_id": "334832094208121942",
      "activity_id": "334460880296576542",
      "coupon_id": "326084653094005537",
      "amount": 0,
      "amount_format": 0.00,
      "prize_order": 2,
      "prize_name": "168元",
      "quantity": 1,
      "coupon_value": 16800,
      "coupon_value_format": "168.00",
      "prize_type": 2,
      "prize_type_format": "优惠券",
      "coupon_type": 1,
      "coupon_type_format": "满减",
      "image_file_id": "334832090572266689",
      "image_url": "https://sili-pr.oss-cn-shenzhen.aliyuncs.com/null"
    }, {
      "prize_id": "334832094208121942",
      "activity_id": "334460880296576542",
      "coupon_id": "326084653094005537",
      "amount": 0,
      "amount_format": 0.00,
      "prize_order": 2,
      "prize_name": "168元",
      "quantity": 1,
      "coupon_value": 16800,
      "coupon_value_format": "168.00",
      "prize_type": 2,
      "prize_type_format": "优惠券",
      "coupon_type": 1,
      "coupon_type_format": "满减",
      "image_file_id": "334832090572266689",
      "image_url": "https://sili-pr.oss-cn-shenzhen.aliyuncs.com/null"
    }, {
      "prize_id": "334832094208121942",
      "activity_id": "334460880296576542",
      "coupon_id": "326084653094005537",
      "amount": 0,
      "amount_format": 0.00,
      "prize_order": 2,
      "prize_name": "168元",
      "quantity": 1,
      "coupon_value": 16800,
      "coupon_value_format": "168.00",
      "prize_type": 2,
      "prize_type_format": "优惠券",
      "coupon_type": 1,
      "coupon_type_format": "满减",
      "image_file_id": "334832090572266689",
      "image_url": "https://sili-pr.oss-cn-shenzhen.aliyuncs.com/null"
    }, {
      "prize_id": "334832094208121942",
      "activity_id": "334460880296576542",
      "coupon_id": "326084653094005537",
      "amount": 0,
      "amount_format": 0.00,
      "prize_order": 2,
      "prize_name": "168元",
      "quantity": 1,
      "coupon_value": 16800,
      "coupon_value_format": "168.00",
      "prize_type": 2,
      "prize_type_format": "优惠券",
      "coupon_type": 1,
      "coupon_type_format": "满减",
      "image_file_id": "334832090572266689",
      "image_url": "https://sili-pr.oss-cn-shenzhen.aliyuncs.com/null"
    }, {
      "prize_id": "334832094208121942",
      "activity_id": "334460880296576542",
      "coupon_id": "326084653094005537",
      "amount": 0,
      "amount_format": 0.00,
      "prize_order": 2,
      "prize_name": "168元",
      "quantity": 1,
      "coupon_value": 16800,
      "coupon_value_format": "168.00",
      "prize_type": 2,
      "prize_type_format": "优惠券",
      "coupon_type": 1,
      "coupon_type_format": "满减",
      "image_file_id": "334832090572266689",
      "image_url": "https://sili-pr.oss-cn-shenzhen.aliyuncs.com/null"
    }, {
      "prize_id": "334832094208121942",
      "activity_id": "334460880296576542",
      "coupon_id": "326084653094005537",
      "amount": 0,
      "amount_format": 0.00,
      "prize_order": 2,
      "prize_name": "168元",
      "quantity": 1,
      "coupon_value": 16800,
      "coupon_value_format": "168.00",
      "prize_type": 2,
      "prize_type_format": "优惠券",
      "coupon_type": 1,
      "coupon_type_format": "满减",
      "image_file_id": "334832090572266689",
      "image_url": "https://sili-pr.oss-cn-shenzhen.aliyuncs.com/null"
    }, {
      "prize_id": "334832094208121942",
      "activity_id": "334460880296576542",
      "coupon_id": "326084653094005537",
      "amount": 0,
      "amount_format": 0.00,
      "prize_order": 2,
      "prize_name": "168元",
      "quantity": 1,
      "coupon_value": 16800,
      "coupon_value_format": "168.00",
      "prize_type": 2,
      "prize_type_format": "优惠券",
      "coupon_type": 1,
      "coupon_type_format": "满减",
      "image_file_id": "334832090572266689",
      "image_url": "https://sili-pr.oss-cn-shenzhen.aliyuncs.com/null"
    }, {
      "prize_id": "334832094208121942",
      "activity_id": "334460880296576542",
      "coupon_id": "326084653094005537",
      "amount": 0,
      "amount_format": 0.00,
      "prize_order": 2,
      "prize_name": "168元",
      "quantity": 1,
      "coupon_value": 16800,
      "coupon_value_format": "168.00",
      "prize_type": 2,
      "prize_type_format": "优惠券",
      "coupon_type": 1,
      "coupon_type_format": "满减",
      "image_file_id": "334832090572266689",
      "image_url": "https://sili-pr.oss-cn-shenzhen.aliyuncs.com/null"
    }, {
      "prize_id": "334832094208121942",
      "activity_id": "334460880296576542",
      "coupon_id": "326084653094005537",
      "amount": 0,
      "amount_format": 0.00,
      "prize_order": 2,
      "prize_name": "168元",
      "quantity": 1,
      "coupon_value": 16800,
      "coupon_value_format": "168.00",
      "prize_type": 2,
      "prize_type_format": "优惠券",
      "coupon_type": 1,
      "coupon_type_format": "满减",
      "image_file_id": "334832090572266689",
      "image_url": "https://sili-pr.oss-cn-shenzhen.aliyuncs.com/null"
    }, {
      "prize_id": "334832094208121942",
      "activity_id": "334460880296576542",
      "coupon_id": "326084653094005537",
      "amount": 0,
      "amount_format": 0.00,
      "prize_order": 2,
      "prize_name": "168元",
      "quantity": 1,
      "coupon_value": 16800,
      "coupon_value_format": "168.00",
      "prize_type": 2,
      "prize_type_format": "优惠券",
      "coupon_type": 1,
      "coupon_type_format": "满减",
      "image_file_id": "334832090572266689",
      "image_url": "https://sili-pr.oss-cn-shenzhen.aliyuncs.com/null"
    }, {
      "prize_id": "334832094208121942",
      "activity_id": "334460880296576542",
      "coupon_id": "326084653094005537",
      "amount": 0,
      "amount_format": 0.00,
      "prize_order": 2,
      "prize_name": "168元",
      "quantity": 1,
      "coupon_value": 16800,
      "coupon_value_format": "168.00",
      "prize_type": 2,
      "prize_type_format": "优惠券",
      "coupon_type": 1,
      "coupon_type_format": "满减",
      "image_file_id": "334832090572266689",
      "image_url": "https://sili-pr.oss-cn-shenzhen.aliyuncs.com/null"
    }, {
      "prize_id": "334832094208121942",
      "activity_id": "334460880296576542",
      "coupon_id": "326084653094005537",
      "amount": 0,
      "amount_format": 0.00,
      "prize_order": 2,
      "prize_name": "168元",
      "quantity": 1,
      "coupon_value": 16800,
      "coupon_value_format": "168.00",
      "prize_type": 2,
      "prize_type_format": "优惠券",
      "coupon_type": 1,
      "coupon_type_format": "满减",
      "image_file_id": "334832090572266689",
      "image_url": "https://sili-pr.oss-cn-shenzhen.aliyuncs.com/null"
    }, {
      "prize_id": "334832094208121942",
      "activity_id": "334460880296576542",
      "coupon_id": "326084653094005537",
      "amount": 0,
      "amount_format": 0.00,
      "prize_order": 2,
      "prize_name": "168元",
      "quantity": 1,
      "coupon_value": 16800,
      "coupon_value_format": "168.00",
      "prize_type": 2,
      "prize_type_format": "优惠券",
      "coupon_type": 1,
      "coupon_type_format": "满减",
      "image_file_id": "334832090572266689",
      "image_url": "https://sili-pr.oss-cn-shenzhen.aliyuncs.com/null"
    }, {
      "prize_id": "334832094208121942",
      "activity_id": "334460880296576542",
      "coupon_id": "326084653094005537",
      "amount": 0,
      "amount_format": 0.00,
      "prize_order": 2,
      "prize_name": "168元",
      "quantity": 1,
      "coupon_value": 16800,
      "coupon_value_format": "168.00",
      "prize_type": 2,
      "prize_type_format": "优惠券",
      "coupon_type": 1,
      "coupon_type_format": "满减",
      "image_file_id": "334832090572266689",
      "image_url": "https://sili-pr.oss-cn-shenzhen.aliyuncs.com/null"
    }, {
      "prize_id": "334832094208121942",
      "activity_id": "334460880296576542",
      "coupon_id": "326084653094005537",
      "amount": 0,
      "amount_format": 0.00,
      "prize_order": 2,
      "prize_name": "168元",
      "quantity": 1,
      "coupon_value": 16800,
      "coupon_value_format": "168.00",
      "prize_type": 2,
      "prize_type_format": "优惠券",
      "coupon_type": 1,
      "coupon_type_format": "满减",
      "image_file_id": "334832090572266689",
      "image_url": "https://sili-pr.oss-cn-shenzhen.aliyuncs.com/null"
    }, {
      "prize_id": "334832094208121942",
      "activity_id": "334460880296576542",
      "coupon_id": "326084653094005537",
      "amount": 0,
      "amount_format": 0.00,
      "prize_order": 2,
      "prize_name": "168元",
      "quantity": 1,
      "coupon_value": 16800,
      "coupon_value_format": "168.00",
      "prize_type": 2,
      "prize_type_format": "优惠券",
      "coupon_type": 1,
      "coupon_type_format": "满减",
      "image_file_id": "334832090572266689",
      "image_url": "https://sili-pr.oss-cn-shenzhen.aliyuncs.com/null"
    }, {
      "prize_id": "334832094208121942",
      "activity_id": "334460880296576542",
      "coupon_id": "326084653094005537",
      "amount": 0,
      "amount_format": 0.00,
      "prize_order": 2,
      "prize_name": "168元",
      "quantity": 1,
      "coupon_value": 16800,
      "coupon_value_format": "168.00",
      "prize_type": 2,
      "prize_type_format": "优惠券",
      "coupon_type": 1,
      "coupon_type_format": "满减",
      "image_file_id": "334832090572266689",
      "image_url": "https://sili-pr.oss-cn-shenzhen.aliyuncs.com/null"
    }, {
      "prize_id": "334832094208121942",
      "activity_id": "334460880296576542",
      "coupon_id": "326084653094005537",
      "amount": 0,
      "amount_format": 0.00,
      "prize_order": 2,
      "prize_name": "168元",
      "quantity": 1,
      "coupon_value": 16800,
      "coupon_value_format": "168.00",
      "prize_type": 2,
      "prize_type_format": "优惠券",
      "coupon_type": 1,
      "coupon_type_format": "满减",
      "image_file_id": "334832090572266689",
      "image_url": "https://sili-pr.oss-cn-shenzhen.aliyuncs.com/null"
    }, {
      "prize_id": "334832094208121942",
      "activity_id": "334460880296576542",
      "coupon_id": "326084653094005537",
      "amount": 0,
      "amount_format": 0.00,
      "prize_order": 2,
      "prize_name": "168元",
      "quantity": 1,
      "coupon_value": 16800,
      "coupon_value_format": "168.00",
      "prize_type": 2,
      "prize_type_format": "优惠券",
      "coupon_type": 1,
      "coupon_type_format": "满减",
      "image_file_id": "334832090572266689",
      "image_url": "https://sili-pr.oss-cn-shenzhen.aliyuncs.com/null"
    }, {
      "prize_id": "334832094208121942",
      "activity_id": "334460880296576542",
      "coupon_id": "326084653094005537",
      "amount": 0,
      "amount_format": 0.00,
      "prize_order": 2,
      "prize_name": "168元",
      "quantity": 1,
      "coupon_value": 16800,
      "coupon_value_format": "168.00",
      "prize_type": 2,
      "prize_type_format": "优惠券",
      "coupon_type": 1,
      "coupon_type_format": "满减",
      "image_file_id": "334832090572266689",
      "image_url": "https://sili-pr.oss-cn-shenzhen.aliyuncs.com/null"
    }, {
      "prize_id": "334832094208121942",
      "activity_id": "334460880296576542",
      "coupon_id": "326084653094005537",
      "amount": 0,
      "amount_format": 0.00,
      "prize_order": 2,
      "prize_name": "168元",
      "quantity": 1,
      "coupon_value": 16800,
      "coupon_value_format": "168.00",
      "prize_type": 2,
      "prize_type_format": "优惠券",
      "coupon_type": 1,
      "coupon_type_format": "满减",
      "image_file_id": "334832090572266689",
      "image_url": "https://sili-pr.oss-cn-shenzhen.aliyuncs.com/null"
    }, {
      "prize_id": "334832094208121942",
      "activity_id": "334460880296576542",
      "coupon_id": "326084653094005537",
      "amount": 0,
      "amount_format": 0.00,
      "prize_order": 2,
      "prize_name": "168元",
      "quantity": 1,
      "coupon_value": 16800,
      "coupon_value_format": "168.00",
      "prize_type": 2,
      "prize_type_format": "优惠券",
      "coupon_type": 1,
      "coupon_type_format": "满减",
      "image_file_id": "334832090572266689",
      "image_url": "https://sili-pr.oss-cn-shenzhen.aliyuncs.com/null"
    }, {
      "prize_id": "334832094208121942",
      "activity_id": "334460880296576542",
      "coupon_id": "326084653094005537",
      "amount": 0,
      "amount_format": 0.00,
      "prize_order": 2,
      "prize_name": "168元",
      "quantity": 1,
      "coupon_value": 16800,
      "coupon_value_format": "168.00",
      "prize_type": 2,
      "prize_type_format": "优惠券",
      "coupon_type": 1,
      "coupon_type_format": "满减",
      "image_file_id": "334832090572266689",
      "image_url": "https://sili-pr.oss-cn-shenzhen.aliyuncs.com/null"
    }, {
      "prize_id": "334832094208121942",
      "activity_id": "334460880296576542",
      "coupon_id": "326084653094005537",
      "amount": 0,
      "amount_format": 0.00,
      "prize_order": 2,
      "prize_name": "168元",
      "quantity": 1,
      "coupon_value": 16800,
      "coupon_value_format": "168.00",
      "prize_type": 2,
      "prize_type_format": "优惠券",
      "coupon_type": 1,
      "coupon_type_format": "满减",
      "image_file_id": "334832090572266689",
      "image_url": "https://sili-pr.oss-cn-shenzhen.aliyuncs.com/null"
    }, {
      "prize_id": "334832094208121942",
      "activity_id": "334460880296576542",
      "coupon_id": "326084653094005537",
      "amount": 0,
      "amount_format": 0.00,
      "prize_order": 2,
      "prize_name": "168元",
      "quantity": 1,
      "coupon_value": 16800,
      "coupon_value_format": "168.00",
      "prize_type": 2,
      "prize_type_format": "优惠券",
      "coupon_type": 1,
      "coupon_type_format": "满减",
      "image_file_id": "334832090572266689",
      "image_url": "https://sili-pr.oss-cn-shenzhen.aliyuncs.com/null"
    }, {
      "prize_id": "334832094208121942",
      "activity_id": "334460880296576542",
      "coupon_id": "326084653094005537",
      "amount": 0,
      "amount_format": 0.00,
      "prize_order": 2,
      "prize_name": "168元",
      "quantity": 1,
      "coupon_value": 16800,
      "coupon_value_format": "168.00",
      "prize_type": 2,
      "prize_type_format": "优惠券",
      "coupon_type": 1,
      "coupon_type_format": "满减",
      "image_file_id": "334832090572266689",
      "image_url": "https://sili-pr.oss-cn-shenzhen.aliyuncs.com/null"
    }, {
      "prize_id": "334832094208121942",
      "activity_id": "334460880296576542",
      "coupon_id": "326084653094005537",
      "amount": 0,
      "amount_format": 0.00,
      "prize_order": 2,
      "prize_name": "168元",
      "quantity": 1,
      "coupon_value": 16800,
      "coupon_value_format": "168.00",
      "prize_type": 2,
      "prize_type_format": "优惠券",
      "coupon_type": 1,
      "coupon_type_format": "满减",
      "image_file_id": "334832090572266689",
      "image_url": "https://sili-pr.oss-cn-shenzhen.aliyuncs.com/null"
    }, {
      "prize_id": "334832094208121942",
      "activity_id": "334460880296576542",
      "coupon_id": "326084653094005537",
      "amount": 0,
      "amount_format": 0.00,
      "prize_order": 2,
      "prize_name": "168元",
      "quantity": 1,
      "coupon_value": 16800,
      "coupon_value_format": "168.00",
      "prize_type": 2,
      "prize_type_format": "优惠券",
      "coupon_type": 1,
      "coupon_type_format": "满减",
      "image_file_id": "334832090572266689",
      "image_url": "https://sili-pr.oss-cn-shenzhen.aliyuncs.com/null"
    }, {
      "prize_id": "334832094208121942",
      "activity_id": "334460880296576542",
      "coupon_id": "326084653094005537",
      "amount": 0,
      "amount_format": 0.00,
      "prize_order": 2,
      "prize_name": "168元",
      "quantity": 1,
      "coupon_value": 16800,
      "coupon_value_format": "168.00",
      "prize_type": 2,
      "prize_type_format": "优惠券",
      "coupon_type": 1,
      "coupon_type_format": "满减",
      "image_file_id": "334832090572266689",
      "image_url": "https://sili-pr.oss-cn-shenzhen.aliyuncs.com/null"
    }, {
      "prize_id": "334832094208121942",
      "activity_id": "334460880296576542",
      "coupon_id": "326084653094005537",
      "amount": 0,
      "amount_format": 0.00,
      "prize_order": 2,
      "prize_name": "168元",
      "quantity": 1,
      "coupon_value": 16800,
      "coupon_value_format": "168.00",
      "prize_type": 2,
      "prize_type_format": "优惠券",
      "coupon_type": 1,
      "coupon_type_format": "满减",
      "image_file_id": "334832090572266689",
      "image_url": "https://sili-pr.oss-cn-shenzhen.aliyuncs.com/null"
    }, {
      "prize_id": "334832094208121942",
      "activity_id": "334460880296576542",
      "coupon_id": "326084653094005537",
      "amount": 0,
      "amount_format": 0.00,
      "prize_order": 2,
      "prize_name": "168元",
      "quantity": 1,
      "coupon_value": 16800,
      "coupon_value_format": "168.00",
      "prize_type": 2,
      "prize_type_format": "优惠券",
      "coupon_type": 1,
      "coupon_type_format": "满减",
      "image_file_id": "334832090572266689",
      "image_url": "https://sili-pr.oss-cn-shenzhen.aliyuncs.com/null"
    }, {
      "prize_id": "334832094208121942",
      "activity_id": "334460880296576542",
      "coupon_id": "326084653094005537",
      "amount": 0,
      "amount_format": 0.00,
      "prize_order": 2,
      "prize_name": "168元",
      "quantity": 1,
      "coupon_value": 16800,
      "coupon_value_format": "168.00",
      "prize_type": 2,
      "prize_type_format": "优惠券",
      "coupon_type": 1,
      "coupon_type_format": "满减",
      "image_file_id": "334832090572266689",
      "image_url": "https://sili-pr.oss-cn-shenzhen.aliyuncs.com/null"
    }, {
      "prize_id": "334832094208121942",
      "activity_id": "334460880296576542",
      "coupon_id": "326084653094005537",
      "amount": 0,
      "amount_format": 0.00,
      "prize_order": 2,
      "prize_name": "168元",
      "quantity": 1,
      "coupon_value": 16800,
      "coupon_value_format": "168.00",
      "prize_type": 2,
      "prize_type_format": "优惠券",
      "coupon_type": 1,
      "coupon_type_format": "满减",
      "image_file_id": "334832090572266689",
      "image_url": "https://sili-pr.oss-cn-shenzhen.aliyuncs.com/null"
    }, {
      "prize_id": "334832094208121942",
      "activity_id": "334460880296576542",
      "coupon_id": "326084653094005537",
      "amount": 0,
      "amount_format": 0.00,
      "prize_order": 2,
      "prize_name": "168元",
      "quantity": 1,
      "coupon_value": 16800,
      "coupon_value_format": "168.00",
      "prize_type": 2,
      "prize_type_format": "优惠券",
      "coupon_type": 1,
      "coupon_type_format": "满减",
      "image_file_id": "334832090572266689",
      "image_url": "https://sili-pr.oss-cn-shenzhen.aliyuncs.com/null"
    }, {
      "prize_id": "334832094208121942",
      "activity_id": "334460880296576542",
      "coupon_id": "326084653094005537",
      "amount": 0,
      "amount_format": 0.00,
      "prize_order": 2,
      "prize_name": "168元",
      "quantity": 1,
      "coupon_value": 16800,
      "coupon_value_format": "168.00",
      "prize_type": 2,
      "prize_type_format": "优惠券",
      "coupon_type": 1,
      "coupon_type_format": "满减",
      "image_file_id": "334832090572266689",
      "image_url": "https://sili-pr.oss-cn-shenzhen.aliyuncs.com/null"
    }, {
      "prize_id": "334832094208121942",
      "activity_id": "334460880296576542",
      "coupon_id": "326084653094005537",
      "amount": 0,
      "amount_format": 0.00,
      "prize_order": 2,
      "prize_name": "168元",
      "quantity": 1,
      "coupon_value": 16800,
      "coupon_value_format": "168.00",
      "prize_type": 2,
      "prize_type_format": "优惠券",
      "coupon_type": 1,
      "coupon_type_format": "满减",
      "image_file_id": "334832090572266689",
      "image_url": "https://sili-pr.oss-cn-shenzhen.aliyuncs.com/null"
    }]
  },
  "success": true,
  "message": "success",
  "statusCode": 200
}
