{
  "data": {
    "box_id": "322472692267211008",
    "online_formatted": "在线",
    "ac": {
      "current_temperature": null,
      "running_mode": null,
      "wind_speed": null,
      "power": null,
      "running_mode_formatted": null
    },
    "body_induction": 2,
    "cells": [
      {
      "goods_name": "王企鹅2",
      "layer_id": "322473123684979210",
      "quantity": 0,
      "layer_no": "1",
      "price": 40,
      "intro": false,
      "real_quantity": 0,
      "floor": [
        [{
          "name": "1",
          "value": null
        }, {
          "name": "2",
          "value": null
        }, {
          "name": "3",
          "value": null
        }, {
          "name": "4",
          "value": null
        }, {
          "name": "5",
          "value": null
        }],
        [{
          "name": "1",
          "value": 0
        }, {
          "name": "2",
          "value": 0
        }, {
          "name": "3",
          "value": 0
        }, {
          "name": "4",
          "value": 0
        }, {
          "name": "5",
          "value": 0
        }]
      ]
    }, 
    {
      "goods_name": "维他菊花茶",
      "layer_id": "322473147661281037",
      "quantity": 4,
      "layer_no": "2",
      "price": 1,
      "intro": false,
      "real_quantity": 4,
      "floor": [
        [{
          "name": "1",
          "value": 0
        }, {
          "name": "2",
          "value": 0
        }, {
          "name": "3",
          "value": 0
        }, {
          "name": "4",
          "value": 0
        }, {
          "name": "5",
          "value": 0
        }],
        [{
          "name": "1",
          "value": 0
        }, {
          "name": "2",
          "value": 0
        }, {
          "name": "3",
          "value": 0
        }, {
          "name": "4",
          "value": 0
        }, {
          "name": "5",
          "value": 0
        }],
        [{
          "name": "1",
          "value": 1
        }, {
          "name": "2",
          "value": 1
        }, {
          "name": "3",
          "value": 1
        }, {
          "name": "4",
          "value": 1
        }, {
          "name": "5",
          "value": 0
        }]
      ]
    }, 
    {
      "goods_name": "维他菊花茶",
      "layer_id": "322473169201872043",
      "quantity": 0,
      "layer_no": "3",
      "price": 2,
      "intro": false,
      "real_quantity": 0,
      "floor": [
        [{
          "name": "1",
          "value": 0
        }, {
          "name": "2",
          "value": 0
        }, {
          "name": "3",
          "value": 0
        }, {
          "name": "4",
          "value": 0
        }, {
          "name": "5",
          "value": 0
        }],
        [{
          "name": "1",
          "value": null
        }, {
          "name": "2",
          "value": null
        }, {
          "name": "3",
          "value": null
        }, {
          "name": "4",
          "value": null
        }, {
          "name": "5",
          "value": null
        }],
        [{
          "name": "1",
          "value": 0
        }, {
          "name": "2",
          "value": 0
        }, {
          "name": "3",
          "value": 0
        }, {
          "name": "4",
          "value": 0
        }, {
          "name": "5",
          "value": 0
        }]
      ]
    }, 
    {
      "goods_name": "怡泉+C",
      "layer_id": "322473220646381207",
      "quantity": 2,
      "layer_no": "4",
      "price": 1,
      "intro": false,
      "real_quantity": 2,
      "floor": [
        [{
          "name": "1",
          "value": 0
        }, {
          "name": "2",
          "value": 0
        }, {
          "name": "3",
          "value": 0
        }, {
          "name": "4",
          "value": 0
        }, {
          "name": "5",
          "value": 0
        }],
        [{
          "name": "1",
          "value": 0
        }, {
          "name": "2",
          "value": 0
        }, {
          "name": "3",
          "value": 0
        }, {
          "name": "4",
          "value": 0
        }, {
          "name": "5",
          "value": 0
        }],
        [{
          "name": "1",
          "value": 0
        }, {
          "name": "2",
          "value": 0
        }, {
          "name": "3",
          "value": 0
        }, {
          "name": "4",
          "value": 0
        }, {
          "name": "5",
          "value": 0
        }],
        [{
          "name": "1",
          "value": 0
        }, {
          "name": "2",
          "value": 0
        }, {
          "name": "3",
          "value": 0
        }, {
          "name": "4",
          "value": 0
        }, {
          "name": "5",
          "value": 0
        }]
      ]
    }, 
    {
      "goods_name": "企鹅王",
      "layer_id": "322473240855198088",
      "quantity": 0,
      "layer_no": "5",
      "price": 10,
      "intro": false,
      "real_quantity": 0,
      "floor": [
        [{
          "name": "1",
          "value": 0
        }, {
          "name": "2",
          "value": 0
        }, {
          "name": "3",
          "value": 0
        }, {
          "name": "4",
          "value": 0
        }, {
          "name": "5",
          "value": 0
        }],
        [{
          "name": "1",
          "value": 0
        }, {
          "name": "2",
          "value": 0
        }, {
          "name": "3",
          "value": 0
        }, {
          "name": "4",
          "value": 0
        }, {
          "name": "5",
          "value": 0
        }]
      ]
    }, 
    {
      "goods_name": "企鹅王",
      "layer_id": "322473273682439177",
      "quantity": 0,
      "layer_no": "6",
      "price": 110,
      "intro": false,
      "real_quantity": 0,
      "floor": [
        [{
          "name": "1",
          "value": 0
        }, {
          "name": "2",
          "value": 0
        }, {
          "name": "3",
          "value": 0
        }, {
          "name": "4",
          "value": 0
        }, {
          "name": "5",
          "value": 0
        }],
        [{
          "name": "1",
          "value": 0
        }, {
          "name": "2",
          "value": 0
        }, {
          "name": "3",
          "value": 0
        }, {
          "name": "4",
          "value": 0
        }, {
          "name": "5",
          "value": 0
        }],
        [{
          "name": "1",
          "value": 0
        }, {
          "name": "2",
          "value": 0
        }, {
          "name": "3",
          "value": 0
        }, {
          "name": "4",
          "value": 0
        }, {
          "name": "5",
          "value": 0
        }],
        [{
          "name": "1",
          "value": 0
        }, {
          "name": "2",
          "value": 0
        }, {
          "name": "3",
          "value": 0
        }, {
          "name": "4",
          "value": 0
        }, {
          "name": "5",
          "value": 0
        }],
        [{
          "name": "1",
          "value": 0
        }, {
          "name": "2",
          "value": 0
        }, {
          "name": "3",
          "value": 0
        }, {
          "name": "4",
          "value": 0
        }, {
          "name": "5",
          "value": 0
        }],
        [{
          "name": "1",
          "value": 0
        }, {
          "name": "2",
          "value": 0
        }, {
          "name": "3",
          "value": 0
        }, {
          "name": "4",
          "value": 0
        }, {
          "name": "5",
          "value": 0
        }]
      ]
    }, 
    {
      "goods_name": "圣安纳珍藏多伦提斯白葡萄酒",
      "layer_id": "322473291550349140",
      "quantity": 0,
      "layer_no": "7",
      "price": 10,
      "intro": false,
      "real_quantity": 0,
      "floor": [
        [{
          "name": "1",
          "value": 0
        }, {
          "name": "2",
          "value": 0
        }, {
          "name": "3",
          "value": 0
        }, {
          "name": "4",
          "value": 0
        }, {
          "name": "5",
          "value": 0
        }],
        [{
          "name": "1",
          "value": 0
        }, {
          "name": "2",
          "value": 0
        }, {
          "name": "3",
          "value": 0
        }, {
          "name": "4",
          "value": 0
        }, {
          "name": "5",
          "value": 0
        }],
        [{
          "name": "1",
          "value": 0
        }, {
          "name": "2",
          "value": 0
        }, {
          "name": "3",
          "value": 0
        }, {
          "name": "4",
          "value": 0
        }, {
          "name": "5",
          "value": 0
        }]
      ]
    }, 
    {
      "goods_name": "胜卡罗橡木桶珍藏红葡萄酒",
      "layer_id": "322473308513558156",
      "quantity": 0,
      "layer_no": "8",
      "price": 2000,
      "intro": false,
      "real_quantity": 0,
      "floor": [
        [{
          "name": "1",
          "value": 0
        }, {
          "name": "2",
          "value": 0
        }, {
          "name": "3",
          "value": 0
        }, {
          "name": "4",
          "value": 0
        }, {
          "name": "5",
          "value": 0
        }],
        [{
          "name": "1",
          "value": 0
        }, {
          "name": "2",
          "value": 0
        }, {
          "name": "3",
          "value": 0
        }, {
          "name": "4",
          "value": 0
        }, {
          "name": "5",
          "value": 0
        }],
        [{
          "name": "1",
          "value": 0
        }, {
          "name": "2",
          "value": 0
        }, {
          "name": "3",
          "value": 0
        }, {
          "name": "4",
          "value": 0
        }, {
          "name": "5",
          "value": 0
        }]
      ]
    }, 
    {
      "goods_name": "CES",
      "layer_id": "322473325797041071",
      "quantity": 0,
      "layer_no": "9",
      "price": 100,
      "intro": false,
      "real_quantity": 0,
      "floor": [
        [{
          "name": "1",
          "value": 0
        }, {
          "name": "2",
          "value": 0
        }, {
          "name": "3",
          "value": 0
        }, {
          "name": "4",
          "value": 0
        }, {
          "name": "5",
          "value": 0
        }],
        [{
          "name": "1",
          "value": 0
        }, {
          "name": "2",
          "value": 0
        }, {
          "name": "3",
          "value": 0
        }, {
          "name": "4",
          "value": 0
        }, {
          "name": "5",
          "value": 0
        }],
        [{
          "name": "1",
          "value": 0
        }, {
          "name": "2",
          "value": 0
        }, {
          "name": "3",
          "value": 0
        }, {
          "name": "4",
          "value": 0
        }, {
          "name": "5",
          "value": 0
        }]
      ]
    }],
    "door_is_open": false,
    "intro": {
      "1": {
        "010308": null
      },
      "2": {
        "020308": null
      },
      "3": {
        "030308": null
      },
      "4": {
        "010408": 0
      },
      "5": {
        "020408": null
      },
      "6": {
        "030408": null
      },
      "7": {
        "011008": 0
      },
      "8": {
        "020608": null
      },
      "9": {
        "031008": null
      }
    },
    "body_induction_formatted": "没人",
    "online": 1,
    "door_is_open_formatted": "关着",
    "lights": [{
      "light_no": null,
      "power": null
    }, {
      "light_no": null,
      "power": null
    }, {
      "light_no": null,
      "power": null
    }]
  },
  "success": true,
  "message": "success",
  "statusCode": 200
}
