{
  "data": [{
      "routerName": "market.html",
      "name": "营销管理",
      "children": [{
          "routerName": null,
          "name": "商品管理",
          "children": [{
              "children": [],
              "routerName": "GoodsCategory",
              "name": "商品分类",
              "id": "010101"
            },
            {
              "children": [],
              "routerName": "Goods",
              "name": "商品列表",
              "id": "010102"
            },
            {
              "children": [],
              "routerName": "Cost",
              "name": "成本录入",
              "id": "010102"
            }
          ]
        },
        {
          "routerName": null,
          "name": "销售管理",
          "children": [{
              "children": [],
              "routerName": "SalesPlan",
              "name": "销售计划",
              "id": "010201"
            },
            {
              "children": [],
              "routerName": "Order",
              "name": "订单列表",
              "id": "010202"
            },
            {
              "children": [],
              "routerName": "OrderCorrection",
              "name": "订单纠正",
              "id": "010205"
            },
            {
              "children": [],
              "routerName": "Invoice",
              "name": "发票列表",
              "id": "010203"
            },
            {
              "children": [],
              "routerName": "InvoiceDetails",
              "name": "开票明细",
              "id": "010204"
            }
          ]
        },
        {
          "routerName": "",
          "name": "库存管理",
          "children": [{
              "children": [],
              "routerName": "Replenishment",
              "name": "补货记录",
              "id": "010401"
            },
            {
              "children": [],
              "routerName": "InventoryChange",
              "name": "库存变动记录",
              "id": "010402"
            },
            {
              "children": [],
              "routerName": "RealTimeInventory",
              "name": "实时库存",
              "id": "010403"
            }
          ]
        },
        {
          "name": "分销中心",
          "routerName": "",
          "children": [{
              "name": "基础设置",
              "routerName": "DistributionBaseSetting"
            },
            {
              "name": "分销商管理",
              "routerName": "DistributorManagement"
            },
            {
              "name": "分销规则",
              "routerName": "DistributorRule"
            },
            {
              "name": "分销订单",
              "routerName": "DistributionOrder"
            }
          ]
        },
        {
          "name": "代购中心",
          "id": "0103",
          "children": [
            {
            "name": "代购规则",
            "id": "010303",
            "routerName": "PurchasingRules"
          },
          {
            "name": "代购申请",
            "id": "010304",
            "routerName": "ApplicationPurchase"
          },
          {
            "name": "审核记录",
            "id": "010305",
            "routerName": "VerificationRecord"
          },
          {
            "name": "代购员管理",
            "id": "010304",
            "routerName": "PurchasingManagement"
          }
        ],
          "routerName": ""
        },
        {
          "name": "优惠劵",
          "id": "0103",
          "children": [{
              "name": "优惠劵列表",
              "id": "010303",
              "routerName": "CouponList"
            },
            {
              "name": "赠劵设置",
              "id": "010304",
              "routerName": "GiftRollSetting"
            },
            {
              "name": "发放设置",
              "id": "010305",
              "routerName": "ReleaseSetting"
            },
            {
              "name": "发放记录",
              "id": "010305",
              "routerName": "ReleaseRecord"
            }
          ],
          "routerName": ""
        },
        {
          "name": "活动管理",
          "id": "0103",
          "children": [{
              "name": "微信抽奖",
              "id": "010303",
              "routerName": "WeChatDraw"
            },
            {
              "name": "推荐有奖",
              "id": "010303",
              "routerName": "RecommendedAwards"
            },
            {
              "name": "随机立减活动设置",
              "routerName": "RandomRemissionSetting"
            },
            {
              "name": "随机立减活动规则",
              "routerName": "RandomRemissionRule"
            }
          ],
          "routerName": ""
        }
      ]
    },
    {
      "routerName": "finance.html",
      "name": "财务管理",
      "children": [{
          "children": [{
              "children": [],
              "routerName": "PendingInspection",
              "name": "待验货",
              "id": "010303"
            },
            {
              "children": [],
              "routerName": "PendingConfirmed",
              "name": "待确认",
              "id": "010304"
            },
            {
              "children": [],
              "routerName": "ReturnInquiry",
              "name": "退货查询",
              "id": "010305"
            },
            {
              "children": [],
              "routerName": "PendingRefund",
              "name": "待退款",
              "id": "010301"
            },
            {
              "children": [],
              "routerName": "PendingReview",
              "name": "待复核",
              "id": "010302"
            }
          ],
          "routerName": null,
          "name": "退货退款",
          "id": "0103"
        },
        {
          "name": "提现申请",
          "id": "0103",
          "children": [{
              "name": "待审核",
              "id": "010303",
              "routerName": "WithdrawPendingReview"
            },
            {
              "name": "待打款",
              "id": "010304",
              "routerName": "PendingPay"
            },
            {
              "name": "已打款",
              "id": "010305",
              "routerName": "AlreadyPay"
            }
          ],
          "routerName": ""
        }
      ]
    },
    {
      "children": [{
          "children": [{
            "routerName": "Replenisher",
            "name": "补货员列表"
          }],
          "routerName": "",
          "name": "补货员管理"
        },
        {
          "children": [{
              "routerName": "Member",
              "name": "会员列表"
            },
            {
              "name": "会员类型列表",
              "routerName": "MemberType"
            }
          ],
          "routerName": "",
          "name": "会员管理"
        }
      ],
      "routerName": "personnel.html",
      "name": "人员管理"
    },
    {
      "children": [{
          "children": [{
              "routerName": "SalesReport",
              "name": "销售报表"
            },
            {
              "routerName": "SalesDetail",
              "name": "销售明细"
            },
            {
              "routerName": "OrderReport",
              "name": "订单报表"
            },
            {
              "routerName": "CollectionDetail",
              "name": "收款明细"
            },
            {
              "routerName": "DailyReceipt",
              "name": "日收款汇总"
            },
            {
              "routerName": "SalesSummary",
              "name": "收款汇总报表"
            }
          ],
          "routerName": "",
          "name": "销售统计"
        },
        {
          "children": [{
              "children": [],
              "routerName": "StockingReport",
              "name": "备货报表 ",
              "id": "020201"
            },
            {
              "children": [],
              "routerName": "ReplenishmentReport",
              "name": "补货报表",
              "id": "020202"
            }
          ],
          "routerName": "",
          "name": "库存统计",
          "id": "0202"
        },
        {
          "children": [{
              "name": "提现流水记录",
              "routerName": "CashFlowRecord"
            },
            {
              "name": "微信抽奖-中奖记录",
              "routerName": "WeChatwinningRecord"
            },
            {
              "name": "推荐有奖-中奖记录",
              "routerName": "WinningNote"
            }
          ],
          "routerName": "",
          "name": "奖励统计",
          "id": "0202"
        },
        {
          "children": [
            {
              "name": "商户分成报表",
              "routerName": "MerchantSplitReport"
            },
            {
              "name": "商户分成统计",
              "routerName": "MerchantShareStatistics"
            }
          ],
          "routerName": "",
          "name": "商户分成",
          "id": "0203"
        }
      ],
      "routerName": "report.html",
      "name": "报表管理",
      "auth_employee_id": "D45996FCFB6F4795B89947594E1942B1",
      "id": "02"
    },
    {
      "routerName": "system.html",
      "name": "系统管理",
      "children": [{
          "children": [{
              "routerName": "BoxManagement",
              "name": "盒子管理"
            },
            {
              "routerName": "MerchantManagement",
              "name": "商户管理"
            },
            {
              "routerName": "ChannelManagement",
              "name": "渠道商管理"
            },
            {
              "routerName": "RegionalManagement",
              "name": "地区管理"
            },
            {
              "routerName": "OperatorManagement",
              "name": "运营商管理"
            }
          ],
          "routerName": "",
          "name": "基本资料"
        },
        {
          "children": [{
              "routerName": "RealTimeStatus",
              "name": "盒子状态"
            },
            {
              "routerName": "Monitor",
              "name": "防盗监控"
            },
            {
              "routerName": "BoxEvent",
              "name": "盒子事件"
            }
          ],
          "routerName": "",
          "name": "盒子监控"
        },
        {
          "children": [{
              "routerName": "RoleManagement",
              "name": "角色管理"
            },
            {
              "routerName": "DepartmentManagement",
              "name": "部门管理"
            },
            {
              "routerName": "EmployeeManagement",
              "name": "员工管理"
            }
          ],
          "routerName": "",
          "name": "权限管理"
        },
        {
          "routerName": "",
          "name": "日志管理",
          "children": [{
            "routerName": "FunctionLog",
            "name": "功能日志"
          }]
        },
        {
          "children": [{
              "routerName": "FirmwareManagement",
              "name": "固件管理"
            },
            {
              "routerName": "BoxUpgrade",
              "name": "盒子升级"
            }
          ],
          "routerName": "",
          "name": "软件管理"
        },
        {
          "name": "官网管理",
          "children": [{
            "name": "留言管理",
            "routerName": "MessageManagement"
          }, {
            "name": "新闻管理",
            "routerName": "NewsManagement"
          }],
          "routerName": ""
        },
        {
          "children": [{
            "resUrl": "",
            "routerName": "MessageSend",
            "name": "消息发送"
          }],
          "routerName": "",
          "name": "客服消息"
        },
        {
          "name": "RFID云端管理",
          "children": [{
              "name": "盒子关联RFID",
              "routerName": "BoxToRFID"
            },
            {
              "name": "RFID关联盒子",
              "routerName": "RFIDToBox"
            }
          ],
          "routerName": ""
        },
        {
          "children": [{
              "resUrl": "",
              "routerName": "MessageSettings",
              "name": "消息设置"
            },
            {
              "resUrl": "",
              "routerName": "MyMessage",
              "name": "我的消息"
            },
            {
              "resUrl": "",
              "routerName": "NotificationCenter",
              "name": "通知中心"
            }
          ],
          "routerName": "",
          "name": "消息管理"
        },
        {
          "children": [
            {
              "resUrl": "",
              "routerName": "AdvertisingManagement",
              "name": "广告管理"
            },
            {
              "resUrl": "",
              "routerName": "TerminalManagement",
              "name": "终端管理"
            }
            
          ],
          "routerName": "",
          "name": "广告中心"
        }
      ]
    },
    {
      "routerName": "workorder.html",
      "name": "工单管理",
      "children": [{
        "routerName": "MyWorkOrder",
        "name": "我的工单"
      }]
    },
    {
      "children": [{
          "children": [{
              "routerName": "AdminSalesReport",
              "name": "销售报表"
            },
            {
              "routerName": "AdminSalesDetail",
              "name": "销售明细"
            },
            {
              "routerName": "AdminOrderReport",
              "name": "订单报表"
            },
            {
              "routerName": "AdminDailyReceipt",
              "name": "日收款汇总"
            },
            {
              "routerName": "AdminSalesSummary",
              "name": "收款汇总报表"
            }
          ],
          "routerName": "",
          "name": "销售统计"
        }
      ],
      "routerName": "admin.html",
      "name": "总部管理",
      "auth_employee_id": "D45996FCFB6F4795B89947594E1942B1",
      "id": "02"
    }
  ],
  "success": true,
  "message": "success",
  "statusCode": 200
}
